nanorag/__init__.py
nanorag/_modidx.py
nanorag/base.py
nanorag/context.py
nanorag/indexing.py
nanorag/llm.py
nanorag/loaders.py
nanorag/store.py
nanorag/utils.py
nanorag-0.0.13.dist-info/LICENSE
nanorag-0.0.13.dist-info/METADATA
nanorag-0.0.13.dist-info/WHEEL
nanorag-0.0.13.dist-info/entry_points.txt
nanorag-0.0.13.dist-info/top_level.txt
nanorag-0.0.13.dist-info/RECORD
