Metadata-Version: 2.1
Name: nanorag
Version: 0.0.13
Summary: Testing doing nanorag with nbdev to try it out
Home-page: https://github.com/antoni0z/nanorag
Author: antoni0z
Author-email: antonioprofesional@proton.me
License: Apache Software License 2.0
Keywords: nbdev jupyter notebook python
Platform: UNKNOWN
Classifier: Development Status :: 4 - Beta
Classifier: Intended Audience :: Developers
Classifier: Natural Language :: English
Classifier: Programming Language :: Python :: 3.7
Classifier: Programming Language :: Python :: 3.8
Classifier: Programming Language :: Python :: 3.9
Classifier: Programming Language :: Python :: 3.10
Classifier: License :: OSI Approved :: Apache Software License
Requires-Python: >=3.7
License-File: LICENSE
Requires-Dist: accelerate
Requires-Dist: pillow
Requires-Dist: polars
Requires-Dist: psycopg2-binary
Requires-Dist: pypdf
Requires-Dist: sentence-transformers
Requires-Dist: torch
Requires-Dist: transformers
Provides-Extra: dev
